pyfa_tool/__init__.py
pyfa_tool/bash_executor.sh
pyfa_tool/lib_functions.py
pyfa_tool/main.py
pyfa_tool/modules/Fa_to_file.R
pyfa_tool/modules/IO.py
pyfa_tool/modules/plotting.py
pyfa_tool/modules/setup_shell_commands.py
pyfa_tool/modules/to_xarray.py
pyfa_tool-0.0.1.dist-info/LICENSE
pyfa_tool-0.0.1.dist-info/METADATA
pyfa_tool-0.0.1.dist-info/WHEEL
pyfa_tool-0.0.1.dist-info/RECORD
