Metadata-Version: 2.1
Name: PyFa-tool
Version: 0.0.1
Summary: A python wrapper on RFa for FA files using Xarray
Author: Thomas Vergauwen
Author-email: thomas.vergauwen@meteo.be
Maintainer: Thomas Vergauwen
Maintainer-email: thomas.vergauwen@meteo.be
Requires-Python: >=3.9,<4.0
Classifier: Programming Language :: Python :: 3
Classifier: Programming Language :: Python :: 3.9
Classifier: Programming Language :: Python :: 3.10
Classifier: Programming Language :: Python :: 3.11
Classifier: Programming Language :: Python :: 3.12
Requires-Dist: geopandas (>=0.12.2,<0.13.0)
Requires-Dist: matplotlib (>=3.6.3,<4.0.0)
Requires-Dist: numpy (>=1.24.1,<2.0.0)
Requires-Dist: pandas (>=1.5.3,<2.0.0)
Requires-Dist: rioxarray (>=0.13.3,<0.14.0)
Requires-Dist: xarray (>=2023.1.0,<2024.0.0)
